my_little_ocr/__init__.py
my_little_ocr/base_engine/__init__.py
my_little_ocr/base_engine/base_ocr_engine.py
my_little_ocr/base_engine/engine_config.py
my_little_ocr/base_engine/img_utils.py
my_little_ocr/ocr_engines/__init__.py
my_little_ocr/ocr_engines/easyocr_engine.py
my_little_ocr/ocr_engines/rapidocr_engine/.gitignore
my_little_ocr/ocr_engines/rapidocr_engine/__init__.py
my_little_ocr/ocr_engines/rapidocr_engine/rapidocr_engine.py
my_little_ocr/ocr_engines/surya_engine.py
my_little_ocr/ocr_engines/tesseract_engine/__init__.py
my_little_ocr/ocr_engines/tesseract_engine/install.py
my_little_ocr/ocr_engines/tesseract_engine/tesseract_engine.py
my_little_ocr/ocr_engines/wechat_ocr_engine/.gitignore
my_little_ocr/ocr_engines/wechat_ocr_engine/__init__.py
my_little_ocr/ocr_engines/wechat_ocr_engine/install.py
my_little_ocr/ocr_engines/wechat_ocr_engine/wechat_ocr_engine.py
my_little_ocr/ocr_engines/wechat_ocr_engine/wechat_ocr_modified_lib.py
my_little_ocr-0.1.0.dist-info/METADATA
my_little_ocr-0.1.0.dist-info/WHEEL
my_little_ocr-0.1.0.dist-info/RECORD
