Metadata-Version: 2.1
Name: my_little_ocr
Version: 0.1.0
Summary: 
License: MIT
Author: X-T-E-R
Author-email: brad8088088@gmail.com
Requires-Python: >=3.10,<3.13
Classifier: License :: OSI Approved :: MIT License
Classifier: Programming Language :: Python :: 3
Classifier: Programming Language :: Python :: 3.10
Classifier: Programming Language :: Python :: 3.11
Classifier: Programming Language :: Python :: 3.12
Provides-Extra: all
Provides-Extra: easyocr
Provides-Extra: rapidocr
Provides-Extra: surya
Provides-Extra: tesseract
Provides-Extra: wechat-ocr
Requires-Dist: easyocr (>=1.7.2,<2.0.0) ; extra == "easyocr" or extra == "all"
Requires-Dist: gitpython (>=3.1.43,<4.0.0)
Requires-Dist: iso639-lang (>=2.4.2,<3.0.0)
Requires-Dist: numpy (<2.0)
Requires-Dist: opencv-python (>=4.10.0.84,<5.0.0.0)
Requires-Dist: pydantic (>=2.9.2,<3.0.0)
Requires-Dist: pytesseract (>=0.3.13,<0.4.0) ; extra == "tesseract" or extra == "all"
Requires-Dist: rapidocr-onnxruntime (>=1.3.24,<2.0.0) ; extra == "rapidocr" or extra == "all"
Requires-Dist: surya-ocr (>=0.5.0,<0.6.0) ; extra == "surya" or extra == "all"
Requires-Dist: wechat-ocr (>=0.0.3,<0.0.4) ; extra == "wechat-ocr" or extra == "all"
